lumodule_pkg/__init__.py
lumodule-0.0.1.dist-info/LICENSE.txt
lumodule-0.0.1.dist-info/METADATA
lumodule-0.0.1.dist-info/WHEEL
lumodule-0.0.1.dist-info/top_level.txt
lumodule-0.0.1.dist-info/RECORD
